frenchnlp/__init__.py
frenchnlp/sentence.py
frenchnlp/utils_xo.py
sphinxext/__init__.py
sphinxext/custom_roles.py
sphinxext/gallery_order.py
sphinxext/github.py
sphinxext/math_symbol_table.py
sphinxext/missing_references.py
sphinxext/mock_gui_toolkits.py
sphinxext/redirect_from.py
sphinxext/skip_deprecated.py
sphinxext/numpydoc/__init__.py
sphinxext/numpydoc/__main__.py
sphinxext/numpydoc/docscrape.py
sphinxext/numpydoc/docscrape_sphinx.py
sphinxext/numpydoc/numpydoc.py
sphinxext/numpydoc/validate.py
sphinxext/numpydoc/xref.py
frenchnlp-0.2.3.dist-info/METADATA
frenchnlp-0.2.3.dist-info/WHEEL
frenchnlp-0.2.3.dist-info/top_level.txt
frenchnlp-0.2.3.dist-info/RECORD
