Metadata-Version: 2.1
Name: frenchnlp
Version: 0.2.3
Summary: State of the art toolchain for natural language processing in French
Home-page: https://github.com/xiaoouwang/frenchnlp
Author: Xiaoou WANG
Author-email: xiaoouwangfrance@gmail.com
License: Apache Licence 2.0
Download-URL: https://pypi.org/project/frenchnlp
Keywords: text mining,npl,corpus,french
Platform: UNKNOWN
Classifier: Programming Language :: Python :: 3
Classifier: License :: OSI Approved :: MIT License
Classifier: Operating System :: OS Independent
Requires-Dist: numpy
Requires-Dist: pandas
Requires-Dist: transformers
Requires-Dist: torch
Requires-Dist: sentence-transformers
Requires-Dist: sklearn
